{
  "folio": "F36V",
  "num_lines": 83,
  "graphs": [
    {
      "line_index": 0,
      "text": "\ufeff# Last edited on 1998-10-07 19:32:13 by stolfi",
      "graph": {
        "nodes": [
          {
            "id": "n0",
            "token": "\ufeff#",
            "rel": null,
            "state": null
          },
          {
            "id": "n1",
            "token": "Last",
            "rel": null,
            "state": null
          },
          {
            "id": "n2",
            "token": "edited",
            "rel": null,
            "state": null
          },
          {
            "id": "n3",
            "token": "on",
            "rel": null,
            "state": null
          },
          {
            "id": "n4",
            "token": "1998-10-07",
            "rel": null,
            "state": null
          },
          {
            "id": "n5",
            "token": "19:32:13",
            "rel": null,
            "state": null
          },
          {
            "id": "n6",
            "token": "by",
            "rel": null,
            "state": "STATE_Y"
          },
          {
            "id": "n7",
            "token": "stolfi",
            "rel": null,
            "state": null
          }
        ],
        "edges": [
          {
            "source": "n0",
            "target": "n1"
          },
          {
            "source": "n1",
            "target": "n2"
          },
          {
            "source": "n2",
            "target": "n3"
          },
          {
            "source": "n3",
            "target": "n4"
          },
          {
            "source": "n4",
            "target": "n5"
          },
          {
            "source": "n5",
            "target": "n6"
          },
          {
            "source": "n6",
            "target": "n7"
          }
        ]
      }
    },
    {
      "line_index": 1,
      "text": "#",
      "graph": {
        "nodes": [
          {
            "id": "n0",
            "token": "#",
            "rel": null,
            "state": null
          }
        ],
        "edges": []
      }
    },
    {
      "line_index": 2,
      "text": "# Identification:",
      "graph": {
        "nodes": [
          {
            "id": "n0",
            "token": "#",
            "rel": null,
            "state": null
          },
          {
            "id": "n1",
            "token": "Identification:",
            "rel": null,
            "state": null
          }
        ],
        "edges": [
          {
            "source": "n0",
            "target": "n1"
          }
        ]
      }
    },
    {
      "line_index": 3,
      "text": "#",
      "graph": {
        "nodes": [
          {
            "id": "n0",
            "token": "#",
            "rel": null,
            "state": null
          }
        ],
        "edges": []
      }
    },
    {
      "line_index": 4,
      "text": "#   Title: ???",
      "graph": {
        "nodes": [
          {
            "id": "n0",
            "token": "#",
            "rel": null,
            "state": null
          },
          {
            "id": "n1",
            "token": "Title:",
            "rel": null,
            "state": null
          },
          {
            "id": "n2",
            "token": "???",
            "rel": null,
            "state": null
          }
        ],
        "edges": [
          {
            "source": "n0",
            "target": "n1"
          },
          {
            "source": "n1",
            "target": "n2"
          }
        ]
      }
    },
    {
      "line_index": 5,
      "text": "#   Page: f36v = EH (Rene) = p070 (Stolfi)",
      "graph": {
        "nodes": [
          {
            "id": "n0",
            "token": "#",
            "rel": null,
            "state": null
          },
          {
            "id": "n1",
            "token": "Page:",
            "rel": null,
            "state": null
          },
          {
            "id": "n2",
            "token": "f36v",
            "rel": null,
            "state": null
          },
          {
            "id": "n3",
            "token": "=",
            "rel": null,
            "state": null
          },
          {
            "id": "n4",
            "token": "EH",
            "rel": null,
            "state": null
          },
          {
            "id": "n5",
            "token": "(Rene)",
            "rel": null,
            "state": null
          },
          {
            "id": "n6",
            "token": "=",
            "rel": null,
            "state": null
          },
          {
            "id": "n7",
            "token": "p070",
            "rel": null,
            "state": null
          },
          {
            "id": "n8",
            "token": "(Stolfi)",
            "rel": null,
            "state": null
          }
        ],
        "edges": [
          {
            "source": "n0",
            "target": "n1"
          },
          {
            "source": "n1",
            "target": "n2"
          },
          {
            "source": "n2",
            "target": "n3"
          },
          {
            "source": "n3",
            "target": "n4"
          },
          {
            "source": "n4",
            "target": "n5"
          },
          {
            "source": "n5",
            "target": "n6"
          },
          {
            "source": "n6",
            "target": "n7"
          },
          {
            "source": "n7",
            "target": "n8"
          }
        ]
      }
    },
    {
      "line_index": 6,
      "text": "#   Folio: f36",
      "graph": {
        "nodes": [
          {
            "id": "n0",
            "token": "#",
            "rel": null,
            "state": null
          },
          {
            "id": "n1",
            "token": "Folio:",
            "rel": null,
            "state": null
          },
          {
            "id": "n2",
            "token": "f36",
            "rel": null,
            "state": null
          }
        ],
        "edges": [
          {
            "source": "n0",
            "target": "n1"
          },
          {
            "source": "n1",
            "target": "n2"
          }
        ]
      }
    },
    {
      "line_index": 7,
      "text": "#   Panels: f36v",
      "graph": {
        "nodes": [
          {
            "id": "n0",
            "token": "#",
            "rel": null,
            "state": null
          },
          {
            "id": "n1",
            "token": "Panels:",
            "rel": null,
            "state": null
          },
          {
            "id": "n2",
            "token": "f36v",
            "rel": null,
            "state": null
          }
        ],
        "edges": [
          {
            "source": "n0",
            "target": "n1"
          },
          {
            "source": "n1",
            "target": "n2"
          }
        ]
      }
    },
    {
      "line_index": 8,
      "text": "#   Bifolio: bE4 = f36+f37",
      "graph": {
        "nodes": [
          {
            "id": "n0",
            "token": "#",
            "rel": null,
            "state": null
          },
          {
            "id": "n1",
            "token": "Bifolio:",
            "rel": null,
            "state": null
          },
          {
            "id": "n2",
            "token": "bE4",
            "rel": null,
            "state": null
          },
          {
            "id": "n3",
            "token": "=",
            "rel": null,
            "state": null
          },
          {
            "id": "n4",
            "token": "f36+f37",
            "rel": null,
            "state": null
          }
        ],
        "edges": [
          {
            "source": "n0",
            "target": "n1"
          },
          {
            "source": "n1",
            "target": "n2"
          },
          {
            "source": "n2",
            "target": "n3"
          },
          {
            "source": "n3",
            "target": "n4"
          }
        ]
      }
    },
    {
      "line_index": 9,
      "text": "#   Quire: E (Rene) = V (Beinecke)",
      "graph": {
        "nodes": [
          {
            "id": "n0",
            "token": "#",
            "rel": null,
            "state": null
          },
          {
            "id": "n1",
            "token": "Quire:",
            "rel": null,
            "state": null
          },
          {
            "id": "n2",
            "token": "E",
            "rel": null,
            "state": null
          },
          {
            "id": "n3",
            "token": "(Rene)",
            "rel": null,
            "state": null
          },
          {
            "id": "n4",
            "token": "=",
            "rel": null,
            "state": null
          },
          {
            "id": "n5",
            "token": "V",
            "rel": null,
            "state": null
          },
          {
            "id": "n6",
            "token": "(Beinecke)",
            "rel": null,
            "state": null
          }
        ],
        "edges": [
          {
            "source": "n0",
            "target": "n1"
          },
          {
            "source": "n1",
            "target": "n2"
          },
          {
            "source": "n2",
            "target": "n3"
          },
          {
            "source": "n3",
            "target": "n4"
          },
          {
            "source": "n4",
            "target": "n5"
          },
          {
            "source": "n5",
            "target": "n6"
          }
        ]
      }
    },
    {
      "line_index": 10,
      "text": "#",
      "graph": {
        "nodes": [
          {
            "id": "n0",
            "token": "#",
            "rel": null,
            "state": null
          }
        ],
        "edges": []
      }
    },
    {
      "line_index": 11,
      "text": "# Attributes:",
      "graph": {
        "nodes": [
          {
            "id": "n0",
            "token": "#",
            "rel": null,
            "state": null
          },
          {
            "id": "n1",
            "token": "Attributes:",
            "rel": null,
            "state": null
          }
        ],
        "edges": [
          {
            "source": "n0",
            "target": "n1"
          }
        ]
      }
    },
    {
      "line_index": 12,
      "text": "#",
      "graph": {
        "nodes": [
          {
            "id": "n0",
            "token": "#",
            "rel": null,
            "state": null
          }
        ],
        "edges": []
      }
    },
    {
      "line_index": 13,
      "text": "#   Language: A (Currier)",
      "graph": {
        "nodes": [
          {
            "id": "n0",
            "token": "#",
            "rel": null,
            "state": null
          },
          {
            "id": "n1",
            "token": "Language:",
            "rel": null,
            "state": null
          },
          {
            "id": "n2",
            "token": "A",
            "rel": null,
            "state": null
          },
          {
            "id": "n3",
            "token": "(Currier)",
            "rel": null,
            "state": null
          }
        ],
        "edges": [
          {
            "source": "n0",
            "target": "n1"
          },
          {
            "source": "n1",
            "target": "n2"
          },
          {
            "source": "n2",
            "target": "n3"
          }
        ]
      }
    },
    {
      "line_index": 14,
      "text": "#   Hand: 1 (Currier)",
      "graph": {
        "nodes": [
          {
            "id": "n0",
            "token": "#",
            "rel": null,
            "state": null
          },
          {
            "id": "n1",
            "token": "Hand:",
            "rel": null,
            "state": null
          },
          {
            "id": "n2",
            "token": "1",
            "rel": null,
            "state": null
          },
          {
            "id": "n3",
            "token": "(Currier)",
            "rel": null,
            "state": null
          }
        ],
        "edges": [
          {
            "source": "n0",
            "target": "n1"
          },
          {
            "source": "n1",
            "target": "n2"
          },
          {
            "source": "n2",
            "target": "n3"
          }
        ]
      }
    },
    {
      "line_index": 15,
      "text": "#   Subsets: H (Rene), hea (Stolfi)",
      "graph": {
        "nodes": [
          {
            "id": "n0",
            "token": "#",
            "rel": null,
            "state": null
          },
          {
            "id": "n1",
            "token": "Subsets:",
            "rel": null,
            "state": null
          },
          {
            "id": "n2",
            "token": "H",
            "rel": null,
            "state": null
          },
          {
            "id": "n3",
            "token": "(Rene),",
            "rel": null,
            "state": null
          },
          {
            "id": "n4",
            "token": "hea",
            "rel": null,
            "state": null
          },
          {
            "id": "n5",
            "token": "(Stolfi)",
            "rel": null,
            "state": null
          }
        ],
        "edges": [
          {
            "source": "n0",
            "target": "n1"
          },
          {
            "source": "n1",
            "target": "n2"
          },
          {
            "source": "n2",
            "target": "n3"
          },
          {
            "source": "n3",
            "target": "n4"
          },
          {
            "source": "n4",
            "target": "n5"
          }
        ]
      }
    },
    {
      "line_index": 16,
      "text": "#   Subject: herbal",
      "graph": {
        "nodes": [
          {
            "id": "n0",
            "token": "#",
            "rel": null,
            "state": null
          },
          {
            "id": "n1",
            "token": "Subject:",
            "rel": null,
            "state": null
          },
          {
            "id": "n2",
            "token": "herbal",
            "rel": null,
            "state": null
          }
        ],
        "edges": [
          {
            "source": "n0",
            "target": "n1"
          },
          {
            "source": "n1",
            "target": "n2"
          }
        ]
      }
    },
    {
      "line_index": 17,
      "text": "#   Colors: green,tan (Reeds)",
      "graph": {
        "nodes": [
          {
            "id": "n0",
            "token": "#",
            "rel": null,
            "state": null
          },
          {
            "id": "n1",
            "token": "Colors:",
            "rel": null,
            "state": null
          },
          {
            "id": "n2",
            "token": "green,tan",
            "rel": null,
            "state": null
          },
          {
            "id": "n3",
            "token": "(Reeds)",
            "rel": null,
            "state": null
          }
        ],
        "edges": [
          {
            "source": "n0",
            "target": "n1"
          },
          {
            "source": "n1",
            "target": "n2"
          },
          {
            "source": "n2",
            "target": "n3"
          }
        ]
      }
    },
    {
      "line_index": 18,
      "text": "#",
      "graph": {
        "nodes": [
          {
            "id": "n0",
            "token": "#",
            "rel": null,
            "state": null
          }
        ],
        "edges": []
      }
    },
    {
      "line_index": 19,
      "text": "# Description:",
      "graph": {
        "nodes": [
          {
            "id": "n0",
            "token": "#",
            "rel": null,
            "state": null
          },
          {
            "id": "n1",
            "token": "Description:",
            "rel": null,
            "state": null
          }
        ],
        "edges": [
          {
            "source": "n0",
            "target": "n1"
          }
        ]
      }
    },
    {
      "line_index": 20,
      "text": "#",
      "graph": {
        "nodes": [
          {
            "id": "n0",
            "token": "#",
            "rel": null,
            "state": null
          }
        ],
        "edges": []
      }
    },
    {
      "line_index": 21,
      "text": "#",
      "graph": {
        "nodes": [
          {
            "id": "n0",
            "token": "#",
            "rel": null,
            "state": null
          }
        ],
        "edges": []
      }
    },
    {
      "line_index": 22,
      "text": "# # <f36v.P> {}",
      "graph": {
        "nodes": [
          {
            "id": "n0",
            "token": "#",
            "rel": null,
            "state": null
          },
          {
            "id": "n1",
            "token": "#",
            "rel": null,
            "state": null
          },
          {
            "id": "n2",
            "token": "<f36v.P>",
            "rel": null,
            "state": null
          },
          {
            "id": "n3",
            "token": "{}",
            "rel": null,
            "state": null
          }
        ],
        "edges": [
          {
            "source": "n0",
            "target": "n1"
          },
          {
            "source": "n1",
            "target": "n2"
          },
          {
            "source": "n2",
            "target": "n3"
          }
        ]
      }
    },
    {
      "line_index": 23,
      "text": "# text",
      "graph": {
        "nodes": [
          {
            "id": "n0",
            "token": "#",
            "rel": null,
            "state": null
          },
          {
            "id": "n1",
            "token": "text",
            "rel": null,
            "state": null
          }
        ],
        "edges": [
          {
            "source": "n0",
            "target": "n1"
          }
        ]
      }
    },
    {
      "line_index": 24,
      "text": "# Last edited on 1998-12-07 06:34:45 by stolfi",
      "graph": {
        "nodes": [
          {
            "id": "n0",
            "token": "#",
            "rel": null,
            "state": null
          },
          {
            "id": "n1",
            "token": "Last",
            "rel": null,
            "state": null
          },
          {
            "id": "n2",
            "token": "edited",
            "rel": null,
            "state": null
          },
          {
            "id": "n3",
            "token": "on",
            "rel": null,
            "state": null
          },
          {
            "id": "n4",
            "token": "1998-12-07",
            "rel": null,
            "state": null
          },
          {
            "id": "n5",
            "token": "06:34:45",
            "rel": null,
            "state": null
          },
          {
            "id": "n6",
            "token": "by",
            "rel": null,
            "state": "STATE_Y"
          },
          {
            "id": "n7",
            "token": "stolfi",
            "rel": null,
            "state": null
          }
        ],
        "edges": [
          {
            "source": "n0",
            "target": "n1"
          },
          {
            "source": "n1",
            "target": "n2"
          },
          {
            "source": "n2",
            "target": "n3"
          },
          {
            "source": "n3",
            "target": "n4"
          },
          {
            "source": "n4",
            "target": "n5"
          },
          {
            "source": "n5",
            "target": "n6"
          },
          {
            "source": "n6",
            "target": "n7"
          }
        ]
      }
    },
    {
      "line_index": 25,
      "text": "#",
      "graph": {
        "nodes": [
          {
            "id": "n0",
            "token": "#",
            "rel": null,
            "state": null
          }
        ],
        "edges": []
      }
    },
    {
      "line_index": 26,
      "text": "<f36v.1,@P0;H>     pcharasy.qoforom.shoaiin.tchey.chckhhy.otaiin.cphar.daiin",
      "graph": {
        "nodes": [
          {
            "id": "n0",
            "token": "<f36v.1,@P0;H>",
            "rel": null,
            "state": null
          },
          {
            "id": "n1",
            "token": "pcharasy.qoforom.shoaiin.tchey.chckhhy.otaiin.cphar.daiin",
            "rel": null,
            "state": "STATE_AIIN"
          }
        ],
        "edges": [
          {
            "source": "n0",
            "target": "n1"
          }
        ]
      }
    },
    {
      "line_index": 27,
      "text": "<f36v.1,@P0;C>     pcharary.qoforom.shoaiin.tchey.chckhey.otaiin.cphar.daiin",
      "graph": {
        "nodes": [
          {
            "id": "n0",
            "token": "<f36v.1,@P0;C>",
            "rel": null,
            "state": null
          },
          {
            "id": "n1",
            "token": "pcharary.qoforom.shoaiin.tchey.chckhey.otaiin.cphar.daiin",
            "rel": null,
            "state": "STATE_AIIN"
          }
        ],
        "edges": [
          {
            "source": "n0",
            "target": "n1"
          }
        ]
      }
    },
    {
      "line_index": 28,
      "text": "<f36v.1,@P0;F>     pcharasy.qoforom.shoaiin.tchey.chckhey.otaiin.cphar.daiin",
      "graph": {
        "nodes": [
          {
            "id": "n0",
            "token": "<f36v.1,@P0;F>",
            "rel": null,
            "state": null
          },
          {
            "id": "n1",
            "token": "pcharasy.qoforom.shoaiin.tchey.chckhey.otaiin.cphar.daiin",
            "rel": null,
            "state": "STATE_AIIN"
          }
        ],
        "edges": [
          {
            "source": "n0",
            "target": "n1"
          }
        ]
      }
    },
    {
      "line_index": 29,
      "text": "#",
      "graph": {
        "nodes": [
          {
            "id": "n0",
            "token": "#",
            "rel": null,
            "state": null
          }
        ],
        "edges": []
      }
    },
    {
      "line_index": 30,
      "text": "<f36v.2,+P0;H>     qotar.chol.daiin.otaiin.qotor.ytar.ochor.chety.ckhor.dom",
      "graph": {
        "nodes": [
          {
            "id": "n0",
            "token": "<f36v.2,+P0;H>",
            "rel": null,
            "state": null
          },
          {
            "id": "n1",
            "token": "qotar.chol.daiin.otaiin.qotor.ytar.ochor.chety.ckhor.dom",
            "rel": "REL_Q",
            "state": null
          }
        ],
        "edges": [
          {
            "source": "n0",
            "target": "n1"
          }
        ]
      }
    },
    {
      "line_index": 31,
      "text": "<f36v.2,+P0;C>     qotar.chol.daiin.otaiin.qotar.ytar.ochor.chety.ckhor.dom",
      "graph": {
        "nodes": [
          {
            "id": "n0",
            "token": "<f36v.2,+P0;C>",
            "rel": null,
            "state": null
          },
          {
            "id": "n1",
            "token": "qotar.chol.daiin.otaiin.qotar.ytar.ochor.chety.ckhor.dom",
            "rel": "REL_Q",
            "state": null
          }
        ],
        "edges": [
          {
            "source": "n0",
            "target": "n1"
          }
        ]
      }
    },
    {
      "line_index": 32,
      "text": "<f36v.2,+P0;F>     qotar.chol.daiin.otaiin.qotor.ytar.ochor.chety.ckhor.dom",
      "graph": {
        "nodes": [
          {
            "id": "n0",
            "token": "<f36v.2,+P0;F>",
            "rel": null,
            "state": null
          },
          {
            "id": "n1",
            "token": "qotar.chol.daiin.otaiin.qotor.ytar.ochor.chety.ckhor.dom",
            "rel": "REL_Q",
            "state": null
          }
        ],
        "edges": [
          {
            "source": "n0",
            "target": "n1"
          }
        ]
      }
    },
    {
      "line_index": 33,
      "text": "#",
      "graph": {
        "nodes": [
          {
            "id": "n0",
            "token": "#",
            "rel": null,
            "state": null
          }
        ],
        "edges": []
      }
    },
    {
      "line_index": 34,
      "text": "<f36v.3,+P0;H>     dchytchy.ytor.s<-><!plant>otaiin.qopchor.otar.otchaiin.s",
      "graph": {
        "nodes": [
          {
            "id": "n0",
            "token": "<f36v.3,+P0;H>",
            "rel": null,
            "state": null
          },
          {
            "id": "n1",
            "token": "dchytchy.ytor.s<-><!plant>otaiin.qopchor.otar.otchaiin.s",
            "rel": null,
            "state": null
          }
        ],
        "edges": [
          {
            "source": "n0",
            "target": "n1"
          }
        ]
      }
    },
    {
      "line_index": 35,
      "text": "<f36v.3,+P0;C>     dchytchy.ytor.s<-><!plant>otaiin.qopchor.otar.otchaiin.s",
      "graph": {
        "nodes": [
          {
            "id": "n0",
            "token": "<f36v.3,+P0;C>",
            "rel": null,
            "state": null
          },
          {
            "id": "n1",
            "token": "dchytchy.ytor.s<-><!plant>otaiin.qopchor.otar.otchaiin.s",
            "rel": null,
            "state": null
          }
        ],
        "edges": [
          {
            "source": "n0",
            "target": "n1"
          }
        ]
      }
    },
    {
      "line_index": 36,
      "text": "<f36v.3,+P0;F>     dchytchy.ytor!s<-><!plant>otaiin.qopchor.otar.otchaiin.s",
      "graph": {
        "nodes": [
          {
            "id": "n0",
            "token": "<f36v.3,+P0;F>",
            "rel": null,
            "state": null
          },
          {
            "id": "n1",
            "token": "dchytchy.ytor!s<-><!plant>otaiin.qopchor.otar.otchaiin.s",
            "rel": null,
            "state": null
          }
        ],
        "edges": [
          {
            "source": "n0",
            "target": "n1"
          }
        ]
      }
    },
    {
      "line_index": 37,
      "text": "#",
      "graph": {
        "nodes": [
          {
            "id": "n0",
            "token": "#",
            "rel": null,
            "state": null
          }
        ],
        "edges": []
      }
    },
    {
      "line_index": 38,
      "text": "<f36v.4,+P0;H>     qotchor.yky.ty.dy<-><!plant>daiin.cthor<$>",
      "graph": {
        "nodes": [
          {
            "id": "n0",
            "token": "<f36v.4,+P0;H>",
            "rel": null,
            "state": null
          },
          {
            "id": "n1",
            "token": "qotchor.yky.ty.dy<-><!plant>daiin.cthor<$>",
            "rel": "REL_Q",
            "state": null
          }
        ],
        "edges": [
          {
            "source": "n0",
            "target": "n1"
          }
        ]
      }
    },
    {
      "line_index": 39,
      "text": "<f36v.4,+P0;C>     qotchor.yky.ty.dy<-><!plant>daiin.cthor<$>",
      "graph": {
        "nodes": [
          {
            "id": "n0",
            "token": "<f36v.4,+P0;C>",
            "rel": null,
            "state": null
          },
          {
            "id": "n1",
            "token": "qotchor.yky.ty.dy<-><!plant>daiin.cthor<$>",
            "rel": "REL_Q",
            "state": null
          }
        ],
        "edges": [
          {
            "source": "n0",
            "target": "n1"
          }
        ]
      }
    },
    {
      "line_index": 40,
      "text": "<f36v.4,+P0;F>     qotchor.yky!ty.dy<-><!plant>daiin.cthor<$>",
      "graph": {
        "nodes": [
          {
            "id": "n0",
            "token": "<f36v.4,+P0;F>",
            "rel": null,
            "state": null
          },
          {
            "id": "n1",
            "token": "qotchor.yky!ty.dy<-><!plant>daiin.cthor<$>",
            "rel": "REL_Q",
            "state": null
          }
        ],
        "edges": [
          {
            "source": "n0",
            "target": "n1"
          }
        ]
      }
    },
    {
      "line_index": 41,
      "text": "#",
      "graph": {
        "nodes": [
          {
            "id": "n0",
            "token": "#",
            "rel": null,
            "state": null
          }
        ],
        "edges": []
      }
    },
    {
      "line_index": 42,
      "text": "<f36v.5,+P1;H>     <!plant>tchor.ckhoiin.daiin.cphchar",
      "graph": {
        "nodes": [
          {
            "id": "n0",
            "token": "<f36v.5,+P1;H>",
            "rel": null,
            "state": null
          },
          {
            "id": "n1",
            "token": "<!plant>tchor.ckhoiin.daiin.cphchar",
            "rel": null,
            "state": null
          }
        ],
        "edges": [
          {
            "source": "n0",
            "target": "n1"
          }
        ]
      }
    },
    {
      "line_index": 43,
      "text": "<f36v.5,+P1;C>     <!plant>tchor.ckhaiin.daiin.cphchar",
      "graph": {
        "nodes": [
          {
            "id": "n0",
            "token": "<f36v.5,+P1;C>",
            "rel": null,
            "state": null
          },
          {
            "id": "n1",
            "token": "<!plant>tchor.ckhaiin.daiin.cphchar",
            "rel": null,
            "state": null
          }
        ],
        "edges": [
          {
            "source": "n0",
            "target": "n1"
          }
        ]
      }
    },
    {
      "line_index": 44,
      "text": "<f36v.5,+P1;F>     <!plant>tchor.ckhoiin.daiin.cphchar",
      "graph": {
        "nodes": [
          {
            "id": "n0",
            "token": "<f36v.5,+P1;F>",
            "rel": null,
            "state": null
          },
          {
            "id": "n1",
            "token": "<!plant>tchor.ckhoiin.daiin.cphchar",
            "rel": null,
            "state": null
          }
        ],
        "edges": [
          {
            "source": "n0",
            "target": "n1"
          }
        ]
      }
    },
    {
      "line_index": 45,
      "text": "#",
      "graph": {
        "nodes": [
          {
            "id": "n0",
            "token": "#",
            "rel": null,
            "state": null
          }
        ],
        "edges": []
      }
    },
    {
      "line_index": 46,
      "text": "<f36v.6,+P1;H>     <!plant>daiin.cthor.daiin.dal.dys",
      "graph": {
        "nodes": [
          {
            "id": "n0",
            "token": "<f36v.6,+P1;H>",
            "rel": null,
            "state": null
          },
          {
            "id": "n1",
            "token": "<!plant>daiin.cthor.daiin.dal.dys",
            "rel": null,
            "state": null
          }
        ],
        "edges": [
          {
            "source": "n0",
            "target": "n1"
          }
        ]
      }
    },
    {
      "line_index": 47,
      "text": "<f36v.6,+P1;C>     <!plant>daiin.cthor.daiin.dal.dys",
      "graph": {
        "nodes": [
          {
            "id": "n0",
            "token": "<f36v.6,+P1;C>",
            "rel": null,
            "state": null
          },
          {
            "id": "n1",
            "token": "<!plant>daiin.cthor.daiin.dal.dys",
            "rel": null,
            "state": null
          }
        ],
        "edges": [
          {
            "source": "n0",
            "target": "n1"
          }
        ]
      }
    },
    {
      "line_index": 48,
      "text": "<f36v.6,+P1;F>     <!plant>daiin.cthor.daiin.dal.dys",
      "graph": {
        "nodes": [
          {
            "id": "n0",
            "token": "<f36v.6,+P1;F>",
            "rel": null,
            "state": null
          },
          {
            "id": "n1",
            "token": "<!plant>daiin.cthor.daiin.dal.dys",
            "rel": null,
            "state": null
          }
        ],
        "edges": [
          {
            "source": "n0",
            "target": "n1"
          }
        ]
      }
    },
    {
      "line_index": 49,
      "text": "#",
      "graph": {
        "nodes": [
          {
            "id": "n0",
            "token": "#",
            "rel": null,
            "state": null
          }
        ],
        "edges": []
      }
    },
    {
      "line_index": 50,
      "text": "<f36v.7,+P1;H>     <!plant>qoky.keol.okchor.os.cho.shan",
      "graph": {
        "nodes": [
          {
            "id": "n0",
            "token": "<f36v.7,+P1;H>",
            "rel": null,
            "state": null
          },
          {
            "id": "n1",
            "token": "<!plant>qoky.keol.okchor.os.cho.shan",
            "rel": null,
            "state": null
          }
        ],
        "edges": [
          {
            "source": "n0",
            "target": "n1"
          }
        ]
      }
    },
    {
      "line_index": 51,
      "text": "<f36v.7,+P1;C>     <!plant>qoky.keol.okchor.os.chy.chan",
      "graph": {
        "nodes": [
          {
            "id": "n0",
            "token": "<f36v.7,+P1;C>",
            "rel": null,
            "state": null
          },
          {
            "id": "n1",
            "token": "<!plant>qoky.keol.okchor.os.chy.chan",
            "rel": null,
            "state": null
          }
        ],
        "edges": [
          {
            "source": "n0",
            "target": "n1"
          }
        ]
      }
    },
    {
      "line_index": 52,
      "text": "<f36v.7,+P1;F>     <!plant>qoky.keol.okchor.os.chy.shan",
      "graph": {
        "nodes": [
          {
            "id": "n0",
            "token": "<f36v.7,+P1;F>",
            "rel": null,
            "state": null
          },
          {
            "id": "n1",
            "token": "<!plant>qoky.keol.okchor.os.chy.shan",
            "rel": null,
            "state": null
          }
        ],
        "edges": [
          {
            "source": "n0",
            "target": "n1"
          }
        ]
      }
    },
    {
      "line_index": 53,
      "text": "#",
      "graph": {
        "nodes": [
          {
            "id": "n0",
            "token": "#",
            "rel": null,
            "state": null
          }
        ],
        "edges": []
      }
    },
    {
      "line_index": 54,
      "text": "<f36v.8,+P1;H>     <!plant>ykshy.ytchy.dol.yty!dy.yky",
      "graph": {
        "nodes": [
          {
            "id": "n0",
            "token": "<f36v.8,+P1;H>",
            "rel": null,
            "state": null
          },
          {
            "id": "n1",
            "token": "<!plant>ykshy.ytchy.dol.yty!dy.yky",
            "rel": null,
            "state": "STATE_Y"
          }
        ],
        "edges": [
          {
            "source": "n0",
            "target": "n1"
          }
        ]
      }
    },
    {
      "line_index": 55,
      "text": "<f36v.8,+P1;C>     <!plant>ykshy.ytchy.dol.yty.dy.yky",
      "graph": {
        "nodes": [
          {
            "id": "n0",
            "token": "<f36v.8,+P1;C>",
            "rel": null,
            "state": null
          },
          {
            "id": "n1",
            "token": "<!plant>ykshy.ytchy.dol.yty.dy.yky",
            "rel": null,
            "state": "STATE_Y"
          }
        ],
        "edges": [
          {
            "source": "n0",
            "target": "n1"
          }
        ]
      }
    },
    {
      "line_index": 56,
      "text": "<f36v.8,+P1;F>     <!plant>ykshy.ytchy.dol.yty!dy.yky",
      "graph": {
        "nodes": [
          {
            "id": "n0",
            "token": "<f36v.8,+P1;F>",
            "rel": null,
            "state": null
          },
          {
            "id": "n1",
            "token": "<!plant>ykshy.ytchy.dol.yty!dy.yky",
            "rel": null,
            "state": "STATE_Y"
          }
        ],
        "edges": [
          {
            "source": "n0",
            "target": "n1"
          }
        ]
      }
    },
    {
      "line_index": 57,
      "text": "#",
      "graph": {
        "nodes": [
          {
            "id": "n0",
            "token": "#",
            "rel": null,
            "state": null
          }
        ],
        "edges": []
      }
    },
    {
      "line_index": 58,
      "text": "<f36v.9,+P1;H>     <!plant>okaiin.ykcholqod.chory",
      "graph": {
        "nodes": [
          {
            "id": "n0",
            "token": "<f36v.9,+P1;H>",
            "rel": null,
            "state": null
          },
          {
            "id": "n1",
            "token": "<!plant>okaiin.ykcholqod.chory",
            "rel": null,
            "state": "STATE_Y"
          }
        ],
        "edges": [
          {
            "source": "n0",
            "target": "n1"
          }
        ]
      }
    },
    {
      "line_index": 59,
      "text": "<f36v.9,+P1;C>     <!plant>okaiin.ykcholqod.chory",
      "graph": {
        "nodes": [
          {
            "id": "n0",
            "token": "<f36v.9,+P1;C>",
            "rel": null,
            "state": null
          },
          {
            "id": "n1",
            "token": "<!plant>okaiin.ykcholqod.chory",
            "rel": null,
            "state": "STATE_Y"
          }
        ],
        "edges": [
          {
            "source": "n0",
            "target": "n1"
          }
        ]
      }
    },
    {
      "line_index": 60,
      "text": "<f36v.9,+P1;F>     <!plant>okaiin.ykcholqod.chory",
      "graph": {
        "nodes": [
          {
            "id": "n0",
            "token": "<f36v.9,+P1;F>",
            "rel": null,
            "state": null
          },
          {
            "id": "n1",
            "token": "<!plant>okaiin.ykcholqod.chory",
            "rel": null,
            "state": "STATE_Y"
          }
        ],
        "edges": [
          {
            "source": "n0",
            "target": "n1"
          }
        ]
      }
    },
    {
      "line_index": 61,
      "text": "#",
      "graph": {
        "nodes": [
          {
            "id": "n0",
            "token": "#",
            "rel": null,
            "state": null
          }
        ],
        "edges": []
      }
    },
    {
      "line_index": 62,
      "text": "<f36v.10,+P1;H>    <!plant>ykcho!tchy.daiin.daii!l!d",
      "graph": {
        "nodes": [
          {
            "id": "n0",
            "token": "<f36v.10,+P1;H>",
            "rel": null,
            "state": null
          },
          {
            "id": "n1",
            "token": "<!plant>ykcho!tchy.daiin.daii!l!d",
            "rel": null,
            "state": null
          }
        ],
        "edges": [
          {
            "source": "n0",
            "target": "n1"
          }
        ]
      }
    },
    {
      "line_index": 63,
      "text": "<f36v.10,+P1;C>    <!plant>ykcho!tchy.daiin.dai!!l.d",
      "graph": {
        "nodes": [
          {
            "id": "n0",
            "token": "<f36v.10,+P1;C>",
            "rel": null,
            "state": null
          },
          {
            "id": "n1",
            "token": "<!plant>ykcho!tchy.daiin.dai!!l.d",
            "rel": null,
            "state": null
          }
        ],
        "edges": [
          {
            "source": "n0",
            "target": "n1"
          }
        ]
      }
    },
    {
      "line_index": 64,
      "text": "<f36v.10,+P1;F>    <!plant>ykcho.tchy.daiin.daiinl!d",
      "graph": {
        "nodes": [
          {
            "id": "n0",
            "token": "<f36v.10,+P1;F>",
            "rel": null,
            "state": null
          },
          {
            "id": "n1",
            "token": "<!plant>ykcho.tchy.daiin.daiinl!d",
            "rel": null,
            "state": null
          }
        ],
        "edges": [
          {
            "source": "n0",
            "target": "n1"
          }
        ]
      }
    },
    {
      "line_index": 65,
      "text": "#",
      "graph": {
        "nodes": [
          {
            "id": "n0",
            "token": "#",
            "rel": null,
            "state": null
          }
        ],
        "edges": []
      }
    },
    {
      "line_index": 66,
      "text": "<f36v.11,+P1;H>    <!plant>oty.chcthy.ytoryd",
      "graph": {
        "nodes": [
          {
            "id": "n0",
            "token": "<f36v.11,+P1;H>",
            "rel": null,
            "state": null
          },
          {
            "id": "n1",
            "token": "<!plant>oty.chcthy.ytoryd",
            "rel": null,
            "state": null
          }
        ],
        "edges": [
          {
            "source": "n0",
            "target": "n1"
          }
        ]
      }
    },
    {
      "line_index": 67,
      "text": "<f36v.11,+P1;C>    <!plant>oty.chcthy.ytoryd",
      "graph": {
        "nodes": [
          {
            "id": "n0",
            "token": "<f36v.11,+P1;C>",
            "rel": null,
            "state": null
          },
          {
            "id": "n1",
            "token": "<!plant>oty.chcthy.ytoryd",
            "rel": null,
            "state": null
          }
        ],
        "edges": [
          {
            "source": "n0",
            "target": "n1"
          }
        ]
      }
    },
    {
      "line_index": 68,
      "text": "<f36v.11,+P1;F>    <!plant>oty!chcthy.ytoryd",
      "graph": {
        "nodes": [
          {
            "id": "n0",
            "token": "<f36v.11,+P1;F>",
            "rel": null,
            "state": null
          },
          {
            "id": "n1",
            "token": "<!plant>oty!chcthy.ytoryd",
            "rel": null,
            "state": null
          }
        ],
        "edges": [
          {
            "source": "n0",
            "target": "n1"
          }
        ]
      }
    },
    {
      "line_index": 69,
      "text": "#",
      "graph": {
        "nodes": [
          {
            "id": "n0",
            "token": "#",
            "rel": null,
            "state": null
          }
        ],
        "edges": []
      }
    },
    {
      "line_index": 70,
      "text": "<f36v.12,+P1;H>    <!plant>ytol.kchy.oty.chd",
      "graph": {
        "nodes": [
          {
            "id": "n0",
            "token": "<f36v.12,+P1;H>",
            "rel": null,
            "state": null
          },
          {
            "id": "n1",
            "token": "<!plant>ytol.kchy.oty.chd",
            "rel": null,
            "state": null
          }
        ],
        "edges": [
          {
            "source": "n0",
            "target": "n1"
          }
        ]
      }
    },
    {
      "line_index": 71,
      "text": "<f36v.12,+P1;C>    <!plant>ytol.kchy.oty.chd",
      "graph": {
        "nodes": [
          {
            "id": "n0",
            "token": "<f36v.12,+P1;C>",
            "rel": null,
            "state": null
          },
          {
            "id": "n1",
            "token": "<!plant>ytol.kchy.oty.chd",
            "rel": null,
            "state": null
          }
        ],
        "edges": [
          {
            "source": "n0",
            "target": "n1"
          }
        ]
      }
    },
    {
      "line_index": 72,
      "text": "<f36v.12,+P1;F>    <!plant>ytol.kchy.oty.chd",
      "graph": {
        "nodes": [
          {
            "id": "n0",
            "token": "<f36v.12,+P1;F>",
            "rel": null,
            "state": null
          },
          {
            "id": "n1",
            "token": "<!plant>ytol.kchy.oty.chd",
            "rel": null,
            "state": null
          }
        ],
        "edges": [
          {
            "source": "n0",
            "target": "n1"
          }
        ]
      }
    },
    {
      "line_index": 73,
      "text": "#",
      "graph": {
        "nodes": [
          {
            "id": "n0",
            "token": "#",
            "rel": null,
            "state": null
          }
        ],
        "edges": []
      }
    },
    {
      "line_index": 74,
      "text": "<f36v.13,+P1;H>    <!plant>oky.she.cthol.oty",
      "graph": {
        "nodes": [
          {
            "id": "n0",
            "token": "<f36v.13,+P1;H>",
            "rel": null,
            "state": null
          },
          {
            "id": "n1",
            "token": "<!plant>oky.she.cthol.oty",
            "rel": null,
            "state": "STATE_Y"
          }
        ],
        "edges": [
          {
            "source": "n0",
            "target": "n1"
          }
        ]
      }
    },
    {
      "line_index": 75,
      "text": "<f36v.13,+P1;C>    <!plant>oky.she.cthol.oty",
      "graph": {
        "nodes": [
          {
            "id": "n0",
            "token": "<f36v.13,+P1;C>",
            "rel": null,
            "state": null
          },
          {
            "id": "n1",
            "token": "<!plant>oky.she.cthol.oty",
            "rel": null,
            "state": "STATE_Y"
          }
        ],
        "edges": [
          {
            "source": "n0",
            "target": "n1"
          }
        ]
      }
    },
    {
      "line_index": 76,
      "text": "<f36v.13,+P1;F>    <!plant>oky.she.cthol.oty",
      "graph": {
        "nodes": [
          {
            "id": "n0",
            "token": "<f36v.13,+P1;F>",
            "rel": null,
            "state": null
          },
          {
            "id": "n1",
            "token": "<!plant>oky.she.cthol.oty",
            "rel": null,
            "state": "STATE_Y"
          }
        ],
        "edges": [
          {
            "source": "n0",
            "target": "n1"
          }
        ]
      }
    },
    {
      "line_index": 77,
      "text": "#",
      "graph": {
        "nodes": [
          {
            "id": "n0",
            "token": "#",
            "rel": null,
            "state": null
          }
        ],
        "edges": []
      }
    },
    {
      "line_index": 78,
      "text": "<f36v.14,+P1;H>    <!plant>soiin.chtain<$>",
      "graph": {
        "nodes": [
          {
            "id": "n0",
            "token": "<f36v.14,+P1;H>",
            "rel": null,
            "state": null
          },
          {
            "id": "n1",
            "token": "<!plant>soiin.chtain<$>",
            "rel": null,
            "state": null
          }
        ],
        "edges": [
          {
            "source": "n0",
            "target": "n1"
          }
        ]
      }
    },
    {
      "line_index": 79,
      "text": "<f36v.14,+P1;C>    <!plant>soiin.chtain<$>",
      "graph": {
        "nodes": [
          {
            "id": "n0",
            "token": "<f36v.14,+P1;C>",
            "rel": null,
            "state": null
          },
          {
            "id": "n1",
            "token": "<!plant>soiin.chtain<$>",
            "rel": null,
            "state": null
          }
        ],
        "edges": [
          {
            "source": "n0",
            "target": "n1"
          }
        ]
      }
    },
    {
      "line_index": 80,
      "text": "<f36v.14,+P1;F>    <!plant>soiin.chtain<$>",
      "graph": {
        "nodes": [
          {
            "id": "n0",
            "token": "<f36v.14,+P1;F>",
            "rel": null,
            "state": null
          },
          {
            "id": "n1",
            "token": "<!plant>soiin.chtain<$>",
            "rel": null,
            "state": null
          }
        ],
        "edges": [
          {
            "source": "n0",
            "target": "n1"
          }
        ]
      }
    },
    {
      "line_index": 81,
      "text": "#",
      "graph": {
        "nodes": [
          {
            "id": "n0",
            "token": "#",
            "rel": null,
            "state": null
          }
        ],
        "edges": []
      }
    },
    {
      "line_index": 82,
      "text": "#",
      "graph": {
        "nodes": [
          {
            "id": "n0",
            "token": "#",
            "rel": null,
            "state": null
          }
        ],
        "edges": []
      }
    }
  ]
}