{
  "folio": "F90V2",
  "total_lines": 62,
  "total_tokens": 161,
  "rel_counts": {},
  "state_counts": {
    "STATE_Y": 7
  },
  "rel_freq": {},
  "state_freq": {
    "STATE_Y": 0.043478260869565216
  },
  "token_length_hist": {
    "2": 10,
    "4": 6,
    "6": 10,
    "10": 4,
    "8": 7,
    "1": 47,
    "15": 25,
    "3": 5,
    "5": 8,
    "7": 6,
    "9": 6,
    "11": 1,
    "21": 1,
    "12": 1,
    "71": 4,
    "69": 3,
    "66": 6,
    "27": 3,
    "67": 3,
    "70": 2,
    "35": 3
  }
}